ros_rosidl_dynamic_typesupport_fastrtps-0.4.1.data/data/include/rosidl_dynamic_typesupport_fastrtps/rosidl_dynamic_typesupport_fastrtps/identifier.h
ros_rosidl_dynamic_typesupport_fastrtps-0.4.1.data/data/include/rosidl_dynamic_typesupport_fastrtps/rosidl_dynamic_typesupport_fastrtps/serialization_support.h
ros_rosidl_dynamic_typesupport_fastrtps-0.4.1.data/data/include/rosidl_dynamic_typesupport_fastrtps/rosidl_dynamic_typesupport_fastrtps/visibility_control.h
ros_rosidl_dynamic_typesupport_fastrtps-0.4.1.data/data/lib/librosidl_dynamic_typesupport_fastrtps.so
ros_rosidl_dynamic_typesupport_fastrtps-0.4.1.data/data/share/ament_index/resource_index/package_run_dependencies/rosidl_dynamic_typesupport_fastrtps
ros_rosidl_dynamic_typesupport_fastrtps-0.4.1.data/data/share/ament_index/resource_index/packages/rosidl_dynamic_typesupport_fastrtps
ros_rosidl_dynamic_typesupport_fastrtps-0.4.1.data/data/share/ament_index/resource_index/parent_prefix_path/rosidl_dynamic_typesupport_fastrtps
ros_rosidl_dynamic_typesupport_fastrtps-0.4.1.data/data/share/rosidl_dynamic_typesupport_fastrtps/local_setup.bash
ros_rosidl_dynamic_typesupport_fastrtps-0.4.1.data/data/share/rosidl_dynamic_typesupport_fastrtps/local_setup.dsv
ros_rosidl_dynamic_typesupport_fastrtps-0.4.1.data/data/share/rosidl_dynamic_typesupport_fastrtps/local_setup.sh
ros_rosidl_dynamic_typesupport_fastrtps-0.4.1.data/data/share/rosidl_dynamic_typesupport_fastrtps/local_setup.zsh
ros_rosidl_dynamic_typesupport_fastrtps-0.4.1.data/data/share/rosidl_dynamic_typesupport_fastrtps/package.dsv
ros_rosidl_dynamic_typesupport_fastrtps-0.4.1.data/data/share/rosidl_dynamic_typesupport_fastrtps/package.xml
ros_rosidl_dynamic_typesupport_fastrtps-0.4.1.data/data/share/rosidl_dynamic_typesupport_fastrtps/cmake/ament_cmake_export_dependencies-extras.cmake
ros_rosidl_dynamic_typesupport_fastrtps-0.4.1.data/data/share/rosidl_dynamic_typesupport_fastrtps/cmake/ament_cmake_export_targets-extras.cmake
ros_rosidl_dynamic_typesupport_fastrtps-0.4.1.dist-info/METADATA
ros_rosidl_dynamic_typesupport_fastrtps-0.4.1.dist-info/WHEEL
ros_rosidl_dynamic_typesupport_fastrtps-0.4.1.dist-info/top_level.txt
ros_rosidl_dynamic_typesupport_fastrtps-0.4.1.dist-info/RECORD
ros_rosidl_dynamic_typesupport_fastrtps-0.4.1.dist-info/licenses/LICENSE
