Metadata-Version: 2.4
Name: ros-rosidl-dynamic-typesupport-fastrtps
Version: 0.4.1
Summary: A ROS package providing FastRTPS-specific dynamic typesupport serialization for manipulating DynamicType and DynamicData objects at runtime.
License-File: LICENSE
Requires-Dist: ros-rosidl-dynamic-typesupport~=0.3.1
Requires-Dist: ros-fastcdr~=2.3.3
Requires-Dist: ros-rcpputils~=2.13.5
Requires-Dist: ros-rcutils~=6.9.8
Requires-Dist: ros-fastdds~=3.2.3
Dynamic: description
Dynamic: description-content-type
Dynamic: license-file
Dynamic: requires-dist
Dynamic: summary
